robustraster/__init__.py
robustraster/dask_cluster_manager.py
robustraster/dask_docker_cluster_manager.py
robustraster/dask_plugins.py
robustraster/earth_engine_auth.py
robustraster/input_driver.py
robustraster/udf_tuner.py
robustraster-0.1.2.dist-info/METADATA
robustraster-0.1.2.dist-info/WHEEL
robustraster-0.1.2.dist-info/top_level.txt
robustraster-0.1.2.dist-info/RECORD
