Metadata-Version: 2.1
Name: robustraster
Version: 0.1.2
Summary: Running user-defined functions on large datasets via out-of-core computation simplfied.
Home-page: 
Author: Adriano Matos
Author-email: adrianom@unr.edu
Classifier: Programming Language :: Python :: 3
Classifier: License :: OSI Approved :: MIT License
Classifier: Operating System :: OS Independent
Requires-Dist: affine==2.4.0
Requires-Dist: attrs==24.2.0
Requires-Dist: bokeh==3.5.2
Requires-Dist: cachetools==5.5.0
Requires-Dist: certifi==2024.8.30
Requires-Dist: cftime==1.6.4
Requires-Dist: charset-normalizer==3.3.2
Requires-Dist: click==8.1.7
Requires-Dist: click-plugins==1.1.1
Requires-Dist: cligj==0.7.2
Requires-Dist: cloudpickle==3.0.0
Requires-Dist: colorama==0.4.6
Requires-Dist: contourpy==1.3.0
Requires-Dist: dask[array,complete,dataframe,diagnostics,distributed]==2024.8.1
Requires-Dist: dask-expr==1.1.11
Requires-Dist: distributed==2024.8.1
Requires-Dist: docker==7.1.0
Requires-Dist: earthengine-api==0.1.417
Requires-Dist: fsspec==2024.9.0
Requires-Dist: google-api-core==2.20.0
Requires-Dist: google-api-python-client==2.146.0
Requires-Dist: google-auth==2.35.0
Requires-Dist: google-auth-httplib2==0.2.0
Requires-Dist: google-cloud-core==2.4.1
Requires-Dist: google-cloud-storage==2.18.2
Requires-Dist: google-crc32c==1.6.0
Requires-Dist: google-resumable-media==2.7.2
Requires-Dist: googleapis-common-protos==1.65.0
Requires-Dist: h5py==3.12.1
Requires-Dist: httplib2==0.22.0
Requires-Dist: idna==3.10
Requires-Dist: importlib-metadata==8.5.0
Requires-Dist: jinja2==3.1.4
Requires-Dist: locket==1.0.0
Requires-Dist: lz4==4.3.3
Requires-Dist: markupsafe==2.1.5
Requires-Dist: msgpack==1.1.0
Requires-Dist: netcdf4==1.7.1.post2
Requires-Dist: numpy==2.0.1
Requires-Dist: packaging==24.1
Requires-Dist: pandas==2.2.2
Requires-Dist: partd==1.4.2
Requires-Dist: pillow==10.4.0
Requires-Dist: proto-plus==1.24.0
Requires-Dist: protobuf==5.28.2
Requires-Dist: psutil==6.0.0
Requires-Dist: pyarrow==17.0.0
Requires-Dist: pyarrow-hotfix==0.6
Requires-Dist: pyasn1==0.6.1
Requires-Dist: pyasn1-modules==0.4.1
Requires-Dist: pyparsing==3.1.4
Requires-Dist: pyproj==3.6.1
Requires-Dist: python-dateutil==2.9.0.post0
Requires-Dist: pytz==2024.2
Requires-Dist: pyyaml==6.0.2
Requires-Dist: rasterio==1.3.11
Requires-Dist: requests==2.32.3
Requires-Dist: rioxarray==0.15.0
Requires-Dist: rsa==4.9
Requires-Dist: six==1.16.0
Requires-Dist: snuggs==1.4.7
Requires-Dist: sortedcontainers==2.4.0
Requires-Dist: tblib==3.0.0
Requires-Dist: toolz==0.12.1
Requires-Dist: tornado==6.4.1
Requires-Dist: tzdata==2024.1
Requires-Dist: uritemplate==4.1.1
Requires-Dist: urllib3==2.2.3
Requires-Dist: xarray[parallel]==2024.9.0
Requires-Dist: xee==0.0.13
Requires-Dist: xyzservices==2024.9.0
Requires-Dist: zict==3.0.0
Requires-Dist: zipp==3.20.2
